{
  "$schema": "https://developer.microsoft.com/json-schemas/fabric/item/report/definition/report/3.2.0/schema.json",
  "themeCollection": {
    "baseTheme": {
      "name": "CY26SU04",
      "reportVersionAtImport": {
        "visual": "2.8.0",
        "report": "3.2.0",
        "page": "2.3.1"
      },
      "type": "SharedResources"
    },
    "customTheme": {
      "name": "Opusline16090060412315188.json",
      "reportVersionAtImport": {
        "visual": "2.8.0",
        "report": "3.2.0",
        "page": "2.3.1"
      },
      "type": "RegisteredResources"
    }
  },
  "objects": {
    "section": [
      {
        "properties": {
          "verticalAlignment": {
            "expr": {
              "Literal": {
                "Value": "'Top'"
              }
            }
          }
        }
      }
    ],
    "outspacePane": [
      {
        "properties": {
          "expanded": {
            "expr": {
              "Literal": {
                "Value": "false"
              }
            }
          }
        }
      }
    ]
  },
  "publicCustomVisuals": [
    "ImageGrid_FC5183B9_926C_45E0_B5F7_0CE9EAF1DA9B",
    "simpleImageEBC4593F96F1425FB3D84C5BF02B5075",
    "bubblechartwithcategoricaldataE827E738ED8C5A16A0737FA72B5905A1",
    "bubbleChartEEDCDFA388784AEEAB47972BC1626196"
  ],
  "resourcePackages": [
    {
      "name": "SharedResources",
      "type": "SharedResources",
      "items": [
        {
          "name": "CY26SU04",
          "path": "BaseThemes/CY26SU04.json",
          "type": "BaseTheme"
        }
      ]
    },
    {
      "name": "RegisteredResources",
      "type": "RegisteredResources",
      "items": [
        {
          "name": "Opusline16090060412315188.json",
          "path": "Opusline16090060412315188.json",
          "type": "CustomTheme"
        },
        {
          "name": "Tela_de_fundo_Vendas7379001721335909.png",
          "path": "Tela_de_fundo_Vendas7379001721335909.png",
          "type": "Image"
        },
        {
          "name": "tela_fundo_produtos8629899758763059.png",
          "path": "tela_fundo_produtos8629899758763059.png",
          "type": "Image"
        }
      ]
    }
  ],
  "settings": {
    "useStylableVisualContainerHeader": true,
    "exportDataMode": "AllowSummarized",
    "defaultDrillFilterOtherVisuals": true,
    "allowChangeFilterTypes": true,
    "useEnhancedTooltips": true,
    "useDefaultAggregateDisplayName": true
  }
}